dialow/__init__.py
dialow/request.py
dialow/response.py
dialow/session.py
pydialogflow-1.0.0.dist-info/METADATA
pydialogflow-1.0.0.dist-info/RECORD
pydialogflow-1.0.0.dist-info/WHEEL
pydialogflow-1.0.0.dist-info/top_level.txt
